protobuf_uml_diagram.py
protobuf_uml_diagram-0.15.dist-info/licenses/LICENSE.txt
protobuf_uml_diagram-0.15.dist-info/METADATA
protobuf_uml_diagram-0.15.dist-info/WHEEL
protobuf_uml_diagram-0.15.dist-info/entry_points.txt
protobuf_uml_diagram-0.15.dist-info/top_level.txt
protobuf_uml_diagram-0.15.dist-info/RECORD
