Metadata-Version: 2.4
Name: protobuf-uml-diagram
Version: 0.15
Summary: Create UML diagrams from Protobuf proto files
Home-page: https://github.com/kinow/protobuf-uml-diagram/
Author: Bruno P. Kinoshita
Author-email: brunodepaulak@yahoo.com.br
Requires-Python: >=3.8
License-File: LICENSE.txt
Requires-Dist: click<8.2,>=7.1
Requires-Dist: graphviz<0.21,>=0.14
Requires-Dist: protobuf<6.32,>=3.13
Provides-Extra: tests
Requires-Dist: codecov==2.1.*; extra == "tests"
Requires-Dist: coverage<7.10,>=5.3; extra == "tests"
Requires-Dist: pytest-cov<6.3,>=2.10; extra == "tests"
Requires-Dist: pytest-env==1.1.5; extra == "tests"
Requires-Dist: pytest-mock<3.15,>=3.11; extra == "tests"
Requires-Dist: pytest<8.5,>=6.1; extra == "tests"
Requires-Dist: pycodestyle<2.14,>=2.6; extra == "tests"
Provides-Extra: all
Requires-Dist: click<8.2,>=7.1; extra == "all"
Requires-Dist: graphviz<0.21,>=0.14; extra == "all"
Requires-Dist: protobuf<6.32,>=3.13; extra == "all"
Requires-Dist: codecov==2.1.*; extra == "all"
Requires-Dist: coverage<7.10,>=5.3; extra == "all"
Requires-Dist: pytest-cov<6.3,>=2.10; extra == "all"
Requires-Dist: pytest-env==1.1.5; extra == "all"
Requires-Dist: pytest-mock<3.15,>=3.11; extra == "all"
Requires-Dist: pytest<8.5,>=6.1; extra == "all"
Requires-Dist: pycodestyle<2.14,>=2.6; extra == "all"
Requires-Dist: mypy==1.*; extra == "all"
Requires-Dist: types-protobuf<6.31,>=4.24; extra == "all"
Dynamic: description
Dynamic: description-content-type
Dynamic: license-file
Dynamic: provides-extra
Dynamic: requires-dist
Dynamic: requires-python
Dynamic: summary
